LICENSE.md
README.md
setup.cfg
setup.py
matts_nflows.egg-info/PKG-INFO
matts_nflows.egg-info/SOURCES.txt
matts_nflows.egg-info/dependency_links.txt
matts_nflows.egg-info/requires.txt
matts_nflows.egg-info/top_level.txt
nflows/__init__.py
nflows/version.py
nflows/distributions/__init__.py
nflows/distributions/base.py
nflows/distributions/discrete.py
nflows/distributions/mixture.py
nflows/distributions/normal.py
nflows/distributions/uniform.py
nflows/flows/__init__.py
nflows/flows/autoregressive.py
nflows/flows/base.py
nflows/flows/realnvp.py
nflows/nn/__init__.py
nflows/nn/nde/__init__.py
nflows/nn/nde/made.py
nflows/nn/nets/__init__.py
nflows/nn/nets/mlp.py
nflows/nn/nets/resnet.py
nflows/transforms/__init__.py
nflows/transforms/autoregressive.py
nflows/transforms/base.py
nflows/transforms/conv.py
nflows/transforms/coupling.py
nflows/transforms/linear.py
nflows/transforms/lu.py
nflows/transforms/made.py
nflows/transforms/nonlinearities.py
nflows/transforms/normalization.py
nflows/transforms/orthogonal.py
nflows/transforms/permutations.py
nflows/transforms/qr.py
nflows/transforms/reshape.py
nflows/transforms/standard.py
nflows/transforms/svd.py
nflows/transforms/UMNN/MonotonicNormalizer.py
nflows/transforms/UMNN/__init__.py
nflows/transforms/splines/__init__.py
nflows/transforms/splines/cubic.py
nflows/transforms/splines/linear.py
nflows/transforms/splines/quadratic.py
nflows/transforms/splines/rational_quadratic.py
nflows/utils/__init__.py
nflows/utils/torchutils.py
nflows/utils/typechecks.py
tests/distributions/__init__.py
tests/distributions/discrete_test.py
tests/distributions/normal_test.py
tests/flows/__init__.py
tests/flows/autoregressive_test.py
tests/flows/base_test.py
tests/flows/realnvp_test.py
tests/transforms/__init__.py
tests/transforms/autoregressive_test.py
tests/transforms/base_test.py
tests/transforms/conv_test.py
tests/transforms/coupling_test.py
tests/transforms/linear_test.py
tests/transforms/lu_test.py
tests/transforms/made_test.py
tests/transforms/nonlinearities_test.py
tests/transforms/normalization_test.py
tests/transforms/orthogonal_test.py
tests/transforms/permutations_test.py
tests/transforms/qr_test.py
