Metadata-Version: 2.1
Name: matts-nflows
Version: 0.14
Summary: Normalizing flows in PyTorch.
Home-page: https://github.com/bayesiains/nflows
Download-URL: https://github.com/bayesiains/nflows/archive/v0.14.tar.gz
Author: Conor Durkan, Artur Bekasov, George Papamakarios, Iain Murray
License: MIT
License-File: LICENSE.md
